sagasu/__init__.py
sagasu/api.py
sagasu/app.py
sagasu/config.py
sagasu/crawler.py
sagasu/engine.py
sagasu/image_captioning.py
sagasu/indexer.py
sagasu/model.py
sagasu/repository.py
sagasu/util.py
sagasu-0.5.3.dist-info/entry_points.txt
sagasu-0.5.3.dist-info/WHEEL
sagasu-0.5.3.dist-info/METADATA
sagasu-0.5.3.dist-info/RECORD
